rsjwt-0.0.4.dist-info/METADATA
rsjwt-0.0.4.dist-info/WHEEL
rsjwt-0.0.4.dist-info/licenses/LICENSE
rsjwt/exceptions.py
rsjwt/__init__.py
rsjwt/__init__.pyi
rsjwt/rsjwt.pypy39-pp73-arm-linux-gnu.so
rsjwt-0.0.4.dist-info/RECORD
