Metadata-Version: 2.4
Name: rsjwt
Version: 0.0.4
Classifier: Programming Language :: Rust
Classifier: Programming Language :: Python :: Implementation :: CPython
Classifier: Programming Language :: Python :: Implementation :: PyPy
Classifier: Programming Language :: Python :: 3
Classifier: Programming Language :: Python :: 3 :: Only
Classifier: Programming Language :: Python :: 3.8
Classifier: Programming Language :: Python :: 3.9
Classifier: Programming Language :: Python :: 3.10
Classifier: Programming Language :: Python :: 3.11
Classifier: Programming Language :: Python :: 3.12
Classifier: Programming Language :: Python :: 3.13
License-File: LICENSE
Summary: Python wrapper for jsonwebtoken from rust
Keywords: jwt,rust
Author-email: Alexander Malev <yttrium@somedev.ru>
Requires-Python: >=3.8
Project-URL: Source Code, https://github.com/aamalev/rsjwt
Project-URL: Issues, https://github.com/aamalev/rsjwt/issues
Project-URL: Documentation, https://github.com/aamalev/rsjwt#using
Project-URL: Changelog, https://github.com/aamalev/rsjwt/releases
